curlformat/VERSION
curlformat/__init__.py
curlformat/bin.py
curlformat/aiohttp/__init__.py
curlformat/aiohttp/api.py
curlformat/aiohttp/generator.py
curlformat/common/__init__.py
curlformat/common/parser.py
curlformat/common/utils.py
curlformat/curl_cffi/__init__.py
curlformat/curl_cffi/api.py
curlformat/curl_cffi/generator.py
curlformat/httpx/__init__.py
curlformat/httpx/api.py
curlformat/httpx/generator.py
curlformat/pycurl/__init__.py
curlformat/pycurl/api.py
curlformat/pycurl/generator.py
curlformat/pyhttpx/__init__.py
curlformat/pyhttpx/api.py
curlformat/pyhttpx/generator.py
curlformat/requests/__init__.py
curlformat/requests/api.py
curlformat/requests/generator.py
curlformat/requests_go/__init__.py
curlformat/requests_go/api.py
curlformat/requests_go/generator.py
curlformat-0.1.4.dist-info/LICENSE
curlformat-0.1.4.dist-info/METADATA
curlformat-0.1.4.dist-info/WHEEL
curlformat-0.1.4.dist-info/entry_points.txt
curlformat-0.1.4.dist-info/top_level.txt
curlformat-0.1.4.dist-info/RECORD
