Metadata-Version: 2.1
Name: curlformat
Version: 0.1.4
Summary: Convert curl commands to Python HTTP client code
Home-page: https://github.com/ihandmine/curlformat
Author: handmine
Author-email: handmine@outlook.com
License: MIT
Keywords: curl
Classifier: Development Status :: 4 - Beta
Classifier: Intended Audience :: Developers
Classifier: License :: OSI Approved :: MIT License
Classifier: Programming Language :: Python
Classifier: Programming Language :: Python :: 3
Classifier: Programming Language :: Python :: 3.7
Classifier: Programming Language :: Python :: 3.8
Classifier: Programming Language :: Python :: 3.9
Classifier: Programming Language :: Python :: 3.10
Classifier: Programming Language :: Python :: 3.11
Classifier: Topic :: Software Development :: Libraries :: Python Modules
Classifier: Topic :: Internet :: WWW/HTTP
Classifier: Operating System :: OS Independent
Requires-Python: >=3.7.0
License-File: LICENSE
Requires-Dist: requests>=2.25.0
Requires-Dist: pyperclip>=1.8.0
Requires-Dist: six>=1.15.0
Provides-Extra: aiohttp
Requires-Dist: aiohttp; extra == "aiohttp"
Provides-Extra: all
Requires-Dist: requests; extra == "all"
Requires-Dist: httpx; extra == "all"
Requires-Dist: aiohttp; extra == "all"
Requires-Dist: pycurl; extra == "all"
Requires-Dist: pyhttpx; extra == "all"
Requires-Dist: curl-cffi; extra == "all"
Requires-Dist: pyperclip; extra == "all"
Provides-Extra: curl_cffi
Requires-Dist: curl-cffi; extra == "curl-cffi"
Provides-Extra: dev
Requires-Dist: pytest; extra == "dev"
Requires-Dist: black; extra == "dev"
Requires-Dist: isort; extra == "dev"
Requires-Dist: mypy; extra == "dev"
Requires-Dist: twine; extra == "dev"
Requires-Dist: wheel; extra == "dev"
Requires-Dist: build; extra == "dev"
Provides-Extra: httpx
Requires-Dist: httpx[http2]>=0.23.0; extra == "httpx"
Provides-Extra: pycurl
Requires-Dist: pycurl; extra == "pycurl"
Provides-Extra: pyhttpx
Requires-Dist: pyhttpx; extra == "pyhttpx"
